karabo_daemontools/bin/envdir
karabo_daemontools/bin/envini
karabo_daemontools/bin/envuidgid
karabo_daemontools/bin/fghack
karabo_daemontools/bin/multilog
karabo_daemontools/bin/pgrphack
karabo_daemontools/bin/readproctitle
karabo_daemontools/bin/setlock
karabo_daemontools/bin/setuidgid
karabo_daemontools/bin/setuser
karabo_daemontools/bin/softlimit
karabo_daemontools/bin/supervise
karabo_daemontools/bin/svc
karabo_daemontools/bin/svok
karabo_daemontools/bin/svscan
karabo_daemontools/bin/svscanboot
karabo_daemontools/bin/svstat
karabo_daemontools/bin/svup
karabo_daemontools/bin/tai64n
karabo_daemontools/bin/tai64nlocal
karabo_daemontools/shims/__init__.py
karabo_daemontools/shims/entrypoints.py
karabo_daemontools-3.0.8.dist-info/METADATA
karabo_daemontools-3.0.8.dist-info/WHEEL
karabo_daemontools-3.0.8.dist-info/entry_points.txt
karabo_daemontools-3.0.8.dist-info/RECORD
