Metadata-Version: 2.4
Name: karabo.daemontools
Version: 3.0.8
Summary: Daemontools for Karabo
Keywords: Karabo,UNIX,services,control system
Author-Email: European XFEL GmbH <opensource@xfel.eu>
Maintainer-Email: "M. Teichmann" <martin.teichmann@xfel.eu>, "S. Hauf" <steffen.hauf@xfel.eu>, "D. Goeries" <dennis.goeries@xfel.eu>
License-Expression: MIT
Classifier: Development Status :: 5 - Production/Stable
Classifier: Intended Audience :: Developers
Classifier: Intended Audience :: Science/Research
Project-URL: Homepage, https://github.com/European-XFEL/Karabo
Project-URL: Bug Reports, https://github.com/European-XFEL/Karabo/issues
Project-URL: Source, https://github.com/European-XFEL/Karabo
Requires-Python: ==3.12.*
